tonik/__init__.py
tonik/api.py
tonik/grafana_annotations.py
tonik/storage.py
tonik/utils.py
tonik/xarray2netcdf.py
tonik/xarray2zarr.py
tonik/package_data/index.html
tonik/package_data/whakaari_labels.json
tonik-0.1.21.dist-info/METADATA
tonik-0.1.21.dist-info/WHEEL
tonik-0.1.21.dist-info/entry_points.txt
tonik-0.1.21.dist-info/licenses/LICENSE
tonik-0.1.21.dist-info/RECORD
